speedlogger.py
speedlogger-1.0.0.dist-info/LICENSE
speedlogger-1.0.0.dist-info/METADATA
speedlogger-1.0.0.dist-info/WHEEL
speedlogger-1.0.0.dist-info/entry_points.txt
speedlogger-1.0.0.dist-info/top_level.txt
speedlogger-1.0.0.dist-info/RECORD
