Metadata-Version: 2.1
Name: speedlogger
Version: 1.0.0
Summary: A Python tool to monitor and log internet speeds using WandB.
Home-page: https://github.com/jin0g/speedlogger
Author: jin0g
Author-email: your.email@example.com
License: UNKNOWN
Platform: UNKNOWN
Requires-Python: >=3.6
License-File: LICENSE
Requires-Dist: speedtest-cli
Requires-Dist: wandb
